LICENSE
README.md
setup.py
memx/__init__.py
memx/main.py
memx.egg-info/PKG-INFO
memx.egg-info/SOURCES.txt
memx.egg-info/dependency_links.txt
memx.egg-info/requires.txt
memx.egg-info/top_level.txt