Metadata-Version: 2.1
Name: memx
Version: 1.0.7
Summary: A Python Library to Manipulate macOS Processes.
Author: Iacob Razvan Mihai
Author-email: razvan.iacob@protonmail.com
License: MIT
Keywords: memory,macos,hacking
Classifier: Development Status :: 5 - Production/Stable
Classifier: Intended Audience :: Developers
Classifier: Programming Language :: Python :: 3
Classifier: License :: OSI Approved :: MIT License
Classifier: Operating System :: MacOS :: MacOS X
License-File: LICENSE
Requires-Dist: psutil
